sisyphus_mirror/__init__.py
sisyphus_mirror/__main__.py
sisyphus_mirror/checks.py
sisyphus_mirror/cli.py
sisyphus_mirror/config.py
sisyphus_mirror/consts.py
sisyphus_mirror/errors.py
sisyphus_mirror/logger.py
sisyphus_mirror/mirror.py
sisyphus_mirror/py.typed
sisyphus_mirror/typedefs.py
sisyphus_mirror-1.2.0.dist-info/licenses/LICENSE
sisyphus_mirror-1.2.0.dist-info/METADATA
sisyphus_mirror-1.2.0.dist-info/WHEEL
sisyphus_mirror-1.2.0.dist-info/entry_points.txt
sisyphus_mirror-1.2.0.dist-info/top_level.txt
sisyphus_mirror-1.2.0.dist-info/RECORD
