Metadata-Version: 2.4
Name: sisyphus-mirror
Version: 1.2.0
Summary: A modern Python implementation of the tool for mirroring the Sisyphus repository.
Author-email: Ruslan Ilyasovich Gilfanov <rigilfanov@yandex.ru>
License-Expression: MIT
Project-URL: Homepage, https://github.com/rigilfanov/sisyphus-mirror-py
Project-URL: Repository, https://github.com/rigilfanov/sisyphus-mirror-py
Project-URL: Issues, https://github.com/rigilfanov/sisyphus-mirror-py/issues
Project-URL: Changelog, https://github.com/rigilfanov/sisyphus-mirror-py/blob/master/CHANGELOG.rst
Keywords: alt,altlinux,linux,mirror,mirroring,repository,sisyphus
Classifier: Development Status :: 5 - Production/Stable
Classifier: Environment :: Console
Classifier: Intended Audience :: System Administrators
Classifier: Operating System :: POSIX :: Linux
Classifier: Programming Language :: Python :: 3
Classifier: Programming Language :: Python :: 3.12
Classifier: Programming Language :: Python :: 3.13
Classifier: Programming Language :: Python :: 3.14
Classifier: Topic :: Internet
Classifier: Topic :: System
Classifier: Topic :: System :: Archiving
Classifier: Topic :: System :: Archiving :: Mirroring
Classifier: Topic :: System :: Systems Administration
Classifier: Topic :: Utilities
Requires-Python: >=3.12
License-File: LICENSE
Dynamic: license-file
